uiseg/__init__.py
uiseg/core.py
uiseg-0.1.0.dist-info/METADATA
uiseg-0.1.0.dist-info/WHEEL
uiseg-0.1.0.dist-info/licenses/LICENSE
uiseg-0.1.0.dist-info/RECORD
