Metadata-Version: 2.4
Name: uiseg
Version: 0.1.0
Summary: Simple UI Segment Lib
Author-email: williamfzc <williamfzc@foxmail.com>
License-File: LICENSE
Requires-Python: >=3.8
Requires-Dist: numpy>=1.24.0
Requires-Dist: opencv-python>=4.8.0
Requires-Dist: pillow>=10.4.0
Requires-Dist: pydantic>=2.10.6
Provides-Extra: dev
Requires-Dist: black>=22.0; extra == 'dev'
Requires-Dist: isort>=5.0; extra == 'dev'
Requires-Dist: pytest>=7.0; extra == 'dev'
